app/__init__.py
app/main.py
app/tools.py
app/commands/__init__.py
app/commands/create.py
app/commands/fix.py
app/commands/initialize.py
app/commands/list_drivers.py
app/commands/login.py
app/commands/update_driver.py
forgekit_cli-0.2.2.dist-info/licenses/LICENSE
forgekit_cli-0.2.2.dist-info/METADATA
forgekit_cli-0.2.2.dist-info/WHEEL
forgekit_cli-0.2.2.dist-info/entry_points.txt
forgekit_cli-0.2.2.dist-info/top_level.txt
forgekit_cli-0.2.2.dist-info/RECORD
