Metadata-Version: 2.4
Name: forgekit-cli
Version: 0.2.2
Summary: AI-assisted project scaffolding CLI
Author-email: Mitchell Long <mitchelltlong@gmail.com>
License: Copyright © 2025 Mitchell Long
Requires-Python: >=3.10
License-File: LICENSE
Requires-Dist: annotated-types==0.7.0
Requires-Dist: anyio==4.9.0
Requires-Dist: beautifulsoup4==4.13.4
Requires-Dist: bs4==0.0.2
Requires-Dist: certifi==2025.6.15
Requires-Dist: charset-normalizer==3.4.2
Requires-Dist: click==8.2.1
Requires-Dist: distro==1.9.0
Requires-Dist: dotenv==0.9.9
Requires-Dist: duckdb==1.3.0
Requires-Dist: h11==0.16.0
Requires-Dist: httpcore==1.0.9
Requires-Dist: httpx==0.28.1
Requires-Dist: idna==3.10
Requires-Dist: jiter==0.10.0
Requires-Dist: markdown-it-py==3.0.0
Requires-Dist: mdurl==0.1.2
Requires-Dist: ollama==0.5.1
Requires-Dist: openai==1.88.0
Requires-Dist: pydantic==2.11.7
Requires-Dist: pydantic_core==2.33.2
Requires-Dist: Pygments==2.19.1
Requires-Dist: python-dotenv==1.1.0
Requires-Dist: requests==2.32.4
Requires-Dist: rich==14.0.0
Requires-Dist: shellingham==1.5.4
Requires-Dist: sniffio==1.3.1
Requires-Dist: soupsieve==2.7
Requires-Dist: typer==0.16.0
Requires-Dist: typing-inspection==0.4.1
Requires-Dist: typing_extensions==4.14.0
Requires-Dist: urllib3==2.5.0
Dynamic: license-file
